casual_mcp_server_weather/__init__.py
casual_mcp_server_weather/cli.py
casual_mcp_server_weather/server.py
casual_mcp_server_weather-1.0.2.dist-info/METADATA
casual_mcp_server_weather-1.0.2.dist-info/WHEEL
casual_mcp_server_weather-1.0.2.dist-info/entry_points.txt
casual_mcp_server_weather-1.0.2.dist-info/top_level.txt
casual_mcp_server_weather-1.0.2.dist-info/RECORD
