Metadata-Version: 2.4
Name: casual-mcp-server-weather
Version: 1.0.2
Summary: Weather and Air quality utilities as an MCP server
Author: Alex Stansfield
License: MIT
Project-URL: Homepage, https://github.com/casualgenius/mcp-servers
Project-URL: Issues, https://github.com/casualgenius/mcp-serverss/issues
Project-URL: Source, https://github.com/casualgenius/mcp-servers
Requires-Python: >=3.11
Requires-Dist: fastmcp
Requires-Dist: pydantic
Requires-Dist: requests
